[
  {
    "carVIN": "5YFP4MCE5NP123789",
    "trueCarID": "PR1978",
    "scrapeDate": "2023-02-24",
    "scrapeURL": "https://www.truecar.com//used-cars-for-sale/listing/5YFP4MCE5NP123789/2022-toyota-corolla/",
    "listingDateDiff": "20 days ago",
    "vehicleHistUseType": "Rental Use",
    "vehicleHistTitleStatus": "Clean",
    "vehicleHistNumOwners": 1,
    "vehicleHistAccidents": 0,
    "transmissionType": "Automatic",
    "fuelType": "Gas",
    "driveType": "FWD",
    "engineInfo": "2.0L Inline-4 Gas",
    "mileage": "3,849",
    "interiorColor": "Light Gray",
    "exteriorColor": "White",
    "style": "Sedan",
    "accidentOwnership": 0,
    "location": "Oklahoma City, OK",
    "mileageRating": "31 cty / 40 hwy",
    "monthlyPayment": "$436/mo",
    "priceClassDiffDirection": null,
    "priceClassDiffPct": "At or near ",
    "priceClassDiffAmt": "avg. list price",
    "priceClassification": "Fair Price",
    "allFeatures": "SE Premium Package ~ 6 Speakers ~ AM/FM radio: SiriusXM ~ Radio data system ~ Radio: Audio ~ Air Conditioning ~ Automatic temperature control ~ Rear window defroster ~ Power steering ~ Power windows ~ Remote keyless entry ~ Steering wheel mounted audio controls ~ Four wheel independent suspension ~ Traction control ~ 4-Wheel Disc Brakes ~ ABS brakes ~ Dual front impact airbags ~ Dual front side impact airbags",
    "listPrice": "$26,287"
  }
]
